{
    "schema_version": "v1",
    "name_for_human": "LobeHub Plugin Finder",
    "name_for_model": "lobehub_plugin_finder",
    "description_for_human": "Finds new plugins for LobeHub",
    "description_for_model": "Finds new plugins for LobeHub. You can search for plugins by category or by keyword.",
    "auth": {
        "type": "none"
    },
    "api": {
        "type": "openapi",
        "url": "https://api.lobehub.com/openapi.json",
        "is_user_authenticated": false
    },
    "logo_url": "https://lobehub.com/images/icon-logo-transparent.png",
    "contact_email": "info@lobehub.com",
    "legal_info_url": "https://www.lobehub.com"
}
